zemberek/__init__.py
zemberek/stemmer.py
zemberek/tokenization.py
pyzemberek-0.0.3.dist-info/LICENSE
pyzemberek-0.0.3.dist-info/METADATA
pyzemberek-0.0.3.dist-info/WHEEL
pyzemberek-0.0.3.dist-info/top_level.txt
pyzemberek-0.0.3.dist-info/RECORD
