Metadata-Version: 2.1
Name: pyzemberek
Version: 0.0.3
Summary: Python implementation of the Turkish NLP library Zemberek.
Home-page: https://github.com/kodiks/pyzemberek
Author: Yavuz Kömeçoğlu
Author-email: yavuz.komecoglu@kodiks.com
License: UNKNOWN
Platform: UNKNOWN
Classifier: Programming Language :: Python :: 3
Classifier: License :: OSI Approved :: Apache Software License
Classifier: Operating System :: OS Independent
Requires-Python: >=3.5
